LICENSE.rst
MANIFEST.in
README.rst
setup.cfg
setup.py
miaou/__init__.py
miaou/app.py
miaou/logger.py
miaou/specs.py
miaou/utils.py
miaou.egg-info/PKG-INFO
miaou.egg-info/SOURCES.txt
miaou.egg-info/dependency_links.txt
miaou.egg-info/not-zip-safe
miaou.egg-info/requires.txt
miaou.egg-info/top_level.txt
miaou/scanner/__init__.py
miaou/scanner/api_scanner.py
miaou/scanner/base.py
miaou/scanner/selenium_scanner.py
test/test.py