Metadata-Version: 2.1
Name: miaou
Version: 0.2.1
Summary: pyzentao spec generator.
Home-page: https://github.com/philip1134/miaou
Author: Philip CHAN
Author-email: philip1134@imior.com
License: MIT
Keywords: Python SDK
Platform: any
Classifier: Development Status :: 4 - Beta
Classifier: Intended Audience :: Developers
Classifier: License :: OSI Approved :: MIT License
Classifier: Operating System :: OS Independent
Classifier: Programming Language :: Python
Classifier: Programming Language :: Python :: 3
Classifier: Programming Language :: Python :: 3.10
Classifier: Topic :: Software Development :: Libraries :: Application Frameworks
Provides-Extra: dev
License-File: LICENSE.rst
